kiwizen/__init__.py
kiwizen/adb/AdbCall.py
kiwizen/adb/__init__.py
kiwizen/alg/IntersectionOf2SpaceLines.py
kiwizen/common/RichLogger.py
kiwizen/common/__init__.py
kiwizen/plt/__init__.py
kiwizen/plt/arrow3d.py
kiwizen/tools/__init__.py
kiwizen/tools/text_diff.py
kiwizen/wechat/__init__.py
kiwizen/wechat/robotwechat.py
kiwizen-0.0.6.dist-info/METADATA
kiwizen-0.0.6.dist-info/WHEEL
kiwizen-0.0.6.dist-info/top_level.txt
kiwizen-0.0.6.dist-info/RECORD
